whatamithinking/jsonproto/__init__.py
whatamithinking/jsonproto/_codec.py
whatamithinking/jsonproto/_common.py
whatamithinking/jsonproto/_constraints.py
whatamithinking/jsonproto/_errors.py
whatamithinking/jsonproto/_issues.py
whatamithinking/jsonproto/_patches.py
whatamithinking/jsonproto/_pointers.py
whatamithinking/jsonproto/_resolver.py
whatamithinking/jsonproto/_struct.py
whatamithinking/jsonproto/_types.py
whatamithinking/jsonproto/_handlers/__init__.py
whatamithinking/jsonproto/_handlers/base.py
whatamithinking/jsonproto/_handlers/bytes.py
whatamithinking/jsonproto/_handlers/mappings.py
whatamithinking/jsonproto/_handlers/models.py
whatamithinking/jsonproto/_handlers/numbers.py
whatamithinking/jsonproto/_handlers/scalars.py
whatamithinking/jsonproto/_handlers/sequences.py
whatamithinking/jsonproto/_handlers/special_forms.py
whatamithinking/jsonproto/_handlers/strings.py
whatamithinking/jsonproto/_handlers/unions.py
whatamithinking_jsonproto-1.1.5.dist-info/METADATA
whatamithinking_jsonproto-1.1.5.dist-info/WHEEL
whatamithinking_jsonproto-1.1.5.dist-info/licenses/LICENSE
whatamithinking_jsonproto-1.1.5.dist-info/RECORD
