Metadata-Version: 2.4
Name: whatamithinking-jsonproto
Version: 1.1.5
Summary: declarative json modeler, validator, encoder, and decoder
Project-URL: Homepage, https://github.com/whatamithinking/jsonproto
Project-URL: Documentation, https://github.com/whatamithinking/jsonproto
Project-URL: Repository, https://github.com/whatamithinking/jsonproto
Project-URL: Issues, https://github.com/whatamithinking/jsonproto/issues
Author-email: Connor Sherwood Maynes <connormaynes@gmail.com>
License-File: LICENSE
Requires-Python: >=3.12
Requires-Dist: lru-dict
Requires-Dist: orjson
Provides-Extra: benchmarks
Requires-Dist: apischema; extra == 'benchmarks'
Requires-Dist: attrs; extra == 'benchmarks'
Requires-Dist: dataclassy; extra == 'benchmarks'
Requires-Dist: mashumaro; extra == 'benchmarks'
Requires-Dist: msgspec; extra == 'benchmarks'
Requires-Dist: psutil; extra == 'benchmarks'
Requires-Dist: pydantic>=2; extra == 'benchmarks'
Requires-Dist: pyserde; extra == 'benchmarks'
Provides-Extra: dev
Requires-Dist: black; extra == 'dev'
Provides-Extra: test
